cloudant/_2to3.py
cloudant/__init__.py
cloudant/_client_session.py
cloudant/_common_util.py
cloudant/_messages.py
cloudant/adapters.py
cloudant/client.py
cloudant/database.py
cloudant/design_document.py
cloudant/document.py
cloudant/error.py
cloudant/feed.py
cloudant/index.py
cloudant/query.py
cloudant/replicator.py
cloudant/result.py
cloudant/scheduler.py
cloudant/security_document.py
cloudant/view.py
cloudant-2.13.0.dist-info/LICENSE
cloudant-2.13.0.dist-info/METADATA
cloudant-2.13.0.dist-info/WHEEL
cloudant-2.13.0.dist-info/top_level.txt
cloudant-2.13.0.dist-info/RECORD
